napari_features/__init__.py
napari_features/_cache.py
napari_features/_dock_widget.py
napari_features/_feature_selection_widget.py
napari_features/_features.py
napari_features/_tree_widget_item.py
napari_features/generator.py
napari_features/_tests/__init__.py
napari_features/_tests/image.png
napari_features/_tests/label.png
napari_features/_tests/test_generator.py
napari_features/data/translations/en.json
napari_features-0.1.4.dist-info/LICENSE
napari_features-0.1.4.dist-info/METADATA
napari_features-0.1.4.dist-info/WHEEL
napari_features-0.1.4.dist-info/entry_points.txt
napari_features-0.1.4.dist-info/top_level.txt
napari_features-0.1.4.dist-info/RECORD
