Metadata-Version: 2.1
Name: napari-features
Version: 0.1.4
Summary: extracts image and object features
Home-page: https://github.com/0x00b1/napari-features
Author: Allen Goodman
Author-email: allen.goodman@icloud.com
License: MIT
Project-URL: Bug Tracker, https://github.com/0x00b1/napari-features/issues
Project-URL: Documentation, https://github.com/0x00b1/napari-features#README.md
Project-URL: Source Code, https://github.com/0x00b1/napari-features
Project-URL: User Support, https://github.com/0x00b1/napari-features/issues
Platform: UNKNOWN
Classifier: Development Status :: 2 - Pre-Alpha
Classifier: Intended Audience :: Developers
Classifier: Framework :: napari
Classifier: Topic :: Software Development :: Testing
Classifier: Programming Language :: Python
Classifier: Programming Language :: Python :: 3
Classifier: Programming Language :: Python :: 3.7
Classifier: Programming Language :: Python :: 3.8
Classifier: Programming Language :: Python :: 3.9
Classifier: Operating System :: OS Independent
Classifier: License :: OSI Approved :: MIT License
Requires-Python: >=3.7
License-File: LICENSE
Requires-Dist: magicgui (>=0.2.9)
Requires-Dist: napari (>=0.4.10)
Requires-Dist: napari-plugin-engine (>=0.1.4)
Requires-Dist: numpy (>=1.19.5)
Requires-Dist: pandas (>=1.2.4)
Requires-Dist: qtpy (>=1.9.0)
Requires-Dist: scikit-image (>=0.18.1)
Requires-Dist: scipy (>=1.4.1)
